PhysicsStruct/VectorSpace3D.py
PhysicsStruct/__init__.py
physicsstruct-1.1.0.dist-info/licenses/LICENSE
physicsstruct-1.1.0.dist-info/METADATA
physicsstruct-1.1.0.dist-info/WHEEL
physicsstruct-1.1.0.dist-info/top_level.txt
physicsstruct-1.1.0.dist-info/RECORD
