Metadata-Version: 2.4
Name: PhysicsStruct
Version: 1.1.0
Summary: A set of classes for physcis variables
Author-email: Whaly-w <whalyforwork@gmail.com>
Project-URL: Homepage, https://github.com/whaly-w/PhysicsStruct
Classifier: Programming Language :: Python :: 3
Classifier: License :: OSI Approved :: MIT License
Classifier: Operating System :: OS Independent
Requires-Python: >=3.8
License-File: LICENSE
Dynamic: license-file
